advisor/__init__.py
advisor/__main__.py
advisor/app.py
advisor/controllers/__init__.py
advisor/controllers/app_controller.py
advisor/controllers/feature_controller.py
advisor/domain/__init__.py
advisor/domain/geometry.py
advisor/domain/unit_converter.py
advisor/domain/core/__init__.py
advisor/domain/core/lab.py
advisor/domain/core/lattice.py
advisor/domain/core/sample.py
advisor/features/__init__.py
advisor/features/scattering_geometry/controllers/__init__.py
advisor/features/scattering_geometry/controllers/scattering_geometry_controller.py
advisor/features/scattering_geometry/domain/__init__.py
advisor/features/scattering_geometry/domain/brillouin_calculator.py
advisor/features/scattering_geometry/domain/core.py
advisor/features/scattering_geometry/ui/__init__.py
advisor/features/scattering_geometry/ui/scattering_geometry_tab.py
advisor/features/scattering_geometry/ui/components/__init__.py
advisor/features/scattering_geometry/ui/components/angles_to_hkl_components.py
advisor/features/scattering_geometry/ui/components/hk_angles_components.py
advisor/features/scattering_geometry/ui/components/hkl_scan_components.py
advisor/features/scattering_geometry/ui/components/hkl_to_angles_components.py
advisor/features/structure_factor/controllers/__init__.py
advisor/features/structure_factor/controllers/structure_factor_controller.py
advisor/features/structure_factor/domain/__init__.py
advisor/features/structure_factor/domain/structure_factor_calculator.py
advisor/features/structure_factor/ui/__init__.py
advisor/features/structure_factor/ui/structure_factor_tab.py
advisor/features/structure_factor/ui/components/__init__.py
advisor/features/structure_factor/ui/components/customized_plane_components.py
advisor/features/structure_factor/ui/components/hkl_plane_components.py
advisor/resources/__init__.py
advisor/resources/icons.qrc
advisor/resources/resources_rc.py
advisor/resources/config/app_config.json
advisor/resources/config/tips.json
advisor/resources/data/nacl.cif
advisor_scattering-0.5.2.dist-info/METADATA
advisor_scattering-0.5.2.dist-info/WHEEL
advisor_scattering-0.5.2.dist-info/entry_points.txt
advisor_scattering-0.5.2.dist-info/top_level.txt
advisor_scattering-0.5.2.dist-info/RECORD
