Metadata-Version: 2.4
Name: advisor-scattering
Version: 0.5.2
Summary: Advisor-Scattering: Advanced Visual X-ray Scattering Toolkit for Reciprocal-space visualization and calculation
Author: Xunyang Hong
License: MIT
Project-URL: Homepage, https://github.com/HongXunyang/advisor
Project-URL: Documentation, https://advisor-scattering.readthedocs.io/en/latest/
Keywords: scattering,reciprocal-space,pyqt,visualization,x-ray scattering,x-ray diffraction
Classifier: Programming Language :: Python :: 3
Classifier: Programming Language :: Python :: 3 :: Only
Classifier: License :: OSI Approved :: MIT License
Classifier: Operating System :: OS Independent
Classifier: Topic :: Scientific/Engineering
Requires-Python: >=3.8
Requires-Dist: PyQt5>=5.15.11
Requires-Dist: matplotlib>=3.9.2
Requires-Dist: numpy>=2.0.2
Requires-Dist: scipy>=1.13.1
Requires-Dist: Dans_Diffraction>=3.3.3
